lxtree/TreeChars.py
lxtree/TreeNode.py
lxtree/__init__.py
lxtree-1.0.0.dist-info/LICENSE
lxtree-1.0.0.dist-info/METADATA
lxtree-1.0.0.dist-info/WHEEL
lxtree-1.0.0.dist-info/top_level.txt
lxtree-1.0.0.dist-info/RECORD
