Metadata-Version: 2.1
Name: lxtree
Version: 1.0.0
Summary: Package to draw tree structures (tree linux command style)
Home-page: https://github.com/salpreh/lxtree
Author: salpreh
Author-email: salva.perez46@gmail.com
License: MIT License
Platform: UNKNOWN
License-File: LICENSE
